check_done/__init__.py
check_done/command.py
check_done/config.py
check_done/done_project_items_info.py
check_done/graphql.py
check_done/info.py
check_done/organization_authentication.py
check_done/queries/organization_projects.graphql
check_done/queries/project_single_select_fields.graphql
check_done/queries/project_v2_items.graphql
check_done/queries/user_projects.graphql
check_done/warning_checks.py
check_done-1.1.0.dist-info/LICENSE
check_done-1.1.0.dist-info/METADATA
check_done-1.1.0.dist-info/WHEEL
check_done-1.1.0.dist-info/entry_points.txt
check_done-1.1.0.dist-info/RECORD
