Metadata-Version: 2.1
Name: check_done
Version: 1.1.0
Summary: Check done issues on a GitHub project board
Home-page: https://github.com/siisurit/check_done
License: MIT
Keywords: check,closed,done,done done,finished,issue,task,validate
Author: Siisurit e.U.
Requires-Python: >=3.11,<3.14
Classifier: Development Status :: 4 - Beta
Classifier: Environment :: Console
Classifier: Intended Audience :: Developers
Classifier: License :: OSI Approved :: MIT License
Classifier: Natural Language :: English
Classifier: Operating System :: OS Independent
Classifier: Programming Language :: Python :: 3
Classifier: Programming Language :: Python :: 3.11
Classifier: Programming Language :: Python :: 3.12
Classifier: Programming Language :: Python :: 3.13
Classifier: Programming Language :: Python :: 3 :: Only
Classifier: Topic :: Software Development
Classifier: Topic :: Software Development :: Quality Assurance
Requires-Dist: cryptography (>=44.0.0,<45.0.0)
Requires-Dist: pydantic (>=2.10.2,<3.0.0)
Requires-Dist: pyjwt (>=2.9.0,<3.0.0)
Requires-Dist: python-dotenv (>=1.0.1,<2.0.0)
Requires-Dist: pyyaml (>=6.0.2,<7.0.0)
Requires-Dist: requests (>=2.32.3,<3.0.0)
Project-URL: Changelog, https://github.com/siisurit/check_done/blob/main/CHANGELOG.md
Project-URL: Documentation, https://github.com/siisurit/check_done/blob/main/README.md
Project-URL: Issue Tracker, https://github.com/siisurit/check_done/issues
Project-URL: Repository, https://github.com/siisurit/check_done.git
